python_code_graph/__init__.py
python_code_graph/cli.py
python_code_graph/analyzers/__init__.py
python_code_graph/analyzers/ast_analyzer.py
python_code_graph/analyzers/import_analyzer.py
python_code_graph/core/__init__.py
python_code_graph/core/code_graph.py
python_code_graph/core/file_processor.py
python_code_graph/utils/__init__.py
python_code_graph/utils/file_utils.py
python_code_graph/utils/logger.py
python_code_graph/utils/queue.py
python_code_graph-0.1.1.dist-info/LICENSE
python_code_graph-0.1.1.dist-info/METADATA
python_code_graph-0.1.1.dist-info/WHEEL
python_code_graph-0.1.1.dist-info/entry_points.txt
python_code_graph-0.1.1.dist-info/top_level.txt
python_code_graph-0.1.1.dist-info/RECORD
