Metadata-Version: 2.1
Name: python-code-graph
Version: 0.1.1
Summary: Generate code graphs for Python projects
Home-page: https://github.com/Aman-s12345/python-code-graph.git
Author: Aman Singh
Author-email: amansinghbiuri@gmail.com
Classifier: Programming Language :: Python :: 3
Classifier: License :: OSI Approved :: MIT License
Classifier: Operating System :: OS Independent
Requires-Python: >=3.8
License-File: LICENSE
